QuantLib/QuantLib.py
QuantLib/_QuantLib.abi3.so
QuantLib/__init__.py
quantlib-1.41.data/data/share/doc/quantlib/LICENSE.TXT
quantlib.libs/libQuantLib-c8ff26e9.so.0.0.0
quantlib-1.41.dist-info/METADATA
quantlib-1.41.dist-info/WHEEL
quantlib-1.41.dist-info/top_level.txt
quantlib-1.41.dist-info/RECORD
